[
    {
        "album": "A Skeletal Domain",
        "albumartist": [
            "Cannibal Corpse"
        ],
        "albumartistid": [
            11
        ],
        "albumid": 15,
        "artist": [
            "Cannibal Corpse"
        ],
        "artistid": [
            11
        ],
        "comment": "",
        "disc": 0,
        "displayartist": "Cannibal Corpse",
        "duration": 246,
        "fanart": "",
        "file": "nfs:\\Music\\Cannibal Corpse - A Skeletal Domain\\01 - High Velocity Impact Spatter.mp3",
        "genre": [
            "Death Metal"
        ],
        "genreid": [
            11
        ],
        "label": "High Velocity Impact Spatter",
        "lastplayed": "",
        "lyrics": "",
        "musicbrainzalbumartistid": "",
        "musicbrainzalbumid": "",
        "musicbrainzartistid": "",
        "musicbrainztrackid": "",
        "playcount": 0,
        "rating": 0,
        "songid": 163,
        "thumbnail": "nfs:\\Music\\Cannibal Corpse - A Skeletal Domain\\Folder.jpg",
        "title": "High Velocity Impact Spatter",
        "track": 1,
        "year": 2014
    },
    {
        "album": "A Skeletal Domain",
        "albumartist": [
            "Cannibal Corpse"
        ],
        "albumartistid": [
            11
        ],
        "albumid": 15,
        "artist": [
            "Cannibal Corpse"
        ],
        "artistid": [
            11
        ],
        "comment": "",
        "disc": 0,
        "displayartist": "Cannibal Corpse",
        "duration": 197,
        "fanart": "",
        "file": "nfs:\\Music\\Cannibal Corpse - A Skeletal Domain\\02 - Sadistic Embodiment.mp3",
        "genre": [
            "Death Metal"
        ],
        "genreid": [
            11
        ],
        "label": "Sadistic Embodiment",
        "lastplayed": "",
        "lyrics": "",
        "musicbrainzalbumartistid": "",
        "musicbrainzalbumid": "",
        "musicbrainzartistid": "",
        "musicbrainztrackid": "",
        "playcount": 0,
        "rating": 0,
        "songid": 164,
        "thumbnail": "nfs:\\Music\\Cannibal Corpse - A Skeletal Domain\\Folder.jpg",
        "title": "Sadistic Embodiment",
        "track": 2,
        "year": 2014
    },
    {
        "album": "A Skeletal Domain",
        "albumartist": [
            "Cannibal Corpse"
        ],
        "albumartistid": [
            11
        ],
        "albumid": 15,
        "artist": [
            "Cannibal Corpse"
        ],
        "artistid": [
            11
        ],
        "comment": "",
        "disc": 0,
        "displayartist": "Cannibal Corpse",
        "duration": 230,
        "fanart": "",
        "file": "nfs:\\Music\\Cannibal Corpse - A Skeletal Domain\\03 - Kill Or Become.mp3",
        "genre": [
            "Death Metal"
        ],
        "genreid": [
            11
        ],
        "label": "Kill Or Become",
        "lastplayed": "",
        "lyrics": "",
        "musicbrainzalbumartistid": "",
        "musicbrainzalbumid": "",
        "musicbrainzartistid": "",
        "musicbrainztrackid": "",
        "playcount": 0,
        "rating": 0,
        "songid": 165,
        "thumbnail": "nfs:\\Music\\Cannibal Corpse - A Skeletal Domain\\Folder.jpg",
        "title": "Kill Or Become",
        "track": 3,
        "year": 2014
    },
    {
        "album": "A Skeletal Domain",
        "albumartist": [
            "Cannibal Corpse"
        ],
        "albumartistid": [
            11
        ],
        "albumid": 15,
        "artist": [
            "Cannibal Corpse"
        ],
        "artistid": [
            11
        ],
        "comment": "",
        "disc": 0,
        "displayartist": "Cannibal Corpse",
        "duration": 218,
        "fanart": "",
        "file": "nfs:\\Music\\Cannibal Corpse - A Skeletal Domain\\04 - A Skeletal Domain.mp3",
        "genre": [
            "Death Metal"
        ],
        "genreid": [
            11
        ],
        "label": "A Skeletal Domain",
        "lastplayed": "",
        "lyrics": "",
        "musicbrainzalbumartistid": "",
        "musicbrainzalbumid": "",
        "musicbrainzartistid": "",
        "musicbrainztrackid": "",
        "playcount": 0,
        "rating": 0,
        "songid": 166,
        "thumbnail": "nfs:\\Music\\Cannibal Corpse - A Skeletal Domain\\Folder.jpg",
        "title": "A Skeletal Domain",
        "track": 4,
        "year": 2014
    },
    {
        "album": "A Skeletal Domain",
        "albumartist": [
            "Cannibal Corpse"
        ],
        "albumartistid": [
            11
        ],
        "albumid": 15,
        "artist": [
            "Cannibal Corpse"
        ],
        "artistid": [
            11
        ],
        "comment": "",
        "disc": 0,
        "displayartist": "Cannibal Corpse",
        "duration": 181,
        "fanart": "",
        "file": "nfs:\\Music\\Cannibal Corpse - A Skeletal Domain\\05 - Headlong Into Carnage.mp3",
        "genre": [
            "Death Metal"
        ],
        "genreid": [
            11
        ],
        "label": "Headlong Into Carnage",
        "lastplayed": "",
        "lyrics": "",
        "musicbrainzalbumartistid": "",
        "musicbrainzalbumid": "",
        "musicbrainzartistid": "",
        "musicbrainztrackid": "",
        "playcount": 0,
        "rating": 0,
        "songid": 167,
        "thumbnail": "nfs:\\Music\\Cannibal Corpse - A Skeletal Domain\\Folder.jpg",
        "title": "Headlong Into Carnage",
        "track": 5,
        "year": 2014
    },
    {
        "album": "A Skeletal Domain",
        "albumartist": [
            "Cannibal Corpse"
        ],
        "albumartistid": [
            11
        ],
        "albumid": 15,
        "artist": [
            "Cannibal Corpse"
        ],
        "artistid": [
            11
        ],
        "comment": "",
        "disc": 0,
        "displayartist": "Cannibal Corpse",
        "duration": 305,
        "fanart": "",
        "file": "nfs:\\Music\\Cannibal Corpse - A Skeletal Domain\\06 - The Murderers Pact.mp3",
        "genre": [
            "Death Metal"
        ],
        "genreid": [
            11
        ],
        "label": "The Murderers Pact",
        "lastplayed": "",
        "lyrics": "",
        "musicbrainzalbumartistid": "",
        "musicbrainzalbumid": "",
        "musicbrainzartistid": "",
        "musicbrainztrackid": "",
        "playcount": 0,
        "rating": 0,
        "songid": 168,
        "thumbnail": "nfs:\\Music\\Cannibal Corpse - A Skeletal Domain\\Folder.jpg",
        "title": "The Murderers Pact",
        "track": 6,
        "year": 2014
    },
    {
        "album": "A Skeletal Domain",
        "albumartist": [
            "Cannibal Corpse"
        ],
        "albumartistid": [
            11
        ],
        "albumid": 15,
        "artist": [
            "Cannibal Corpse"
        ],
        "artistid": [
            11
        ],
        "comment": "",
        "disc": 0,
        "displayartist": "Cannibal Corpse",
        "duration": 221,
        "fanart": "",
        "file": "nfs:\\Music\\Cannibal Corpse - A Skeletal Domain\\07 - Funeral Cremation.mp3",
        "genre": [
            "Death Metal"
        ],
        "genreid": [
            11
        ],
        "label": "Funeral Cremation",
        "lastplayed": "",
        "lyrics": "",
        "musicbrainzalbumartistid": "",
        "musicbrainzalbumid": "",
        "musicbrainzartistid": "",
        "musicbrainztrackid": "",
        "playcount": 0,
        "rating": 0,
        "songid": 169,
        "thumbnail": "nfs:\\Music\\Cannibal Corpse - A Skeletal Domain\\Folder.jpg",
        "title": "Funeral Cremation",
        "track": 7,
        "year": 2014
    },
    {
        "album": "A Skeletal Domain",
        "albumartist": [
            "Cannibal Corpse"
        ],
        "albumartistid": [
            11
        ],
        "albumid": 15,
        "artist": [
            "Cannibal Corpse"
        ],
        "artistid": [
            11
        ],
        "comment": "",
        "disc": 0,
        "displayartist": "Cannibal Corpse",
        "duration": 196,
        "fanart": "",
        "file": "nfs:\\Music\\Cannibal Corpse - A Skeletal Domain\\08 - Icepick Lobotomy.mp3",
        "genre": [
            "Death Metal"
        ],
        "genreid": [
            11
        ],
        "label": "Icepick Lobotomy",
        "lastplayed": "",
        "lyrics": "",
        "musicbrainzalbumartistid": "",
        "musicbrainzalbumid": "",
        "musicbrainzartistid": "",
        "musicbrainztrackid": "",
        "playcount": 0,
        "rating": 0,
        "songid": 170,
        "thumbnail": "nfs:\\Music\\Cannibal Corpse - A Skeletal Domain\\Folder.jpg",
        "title": "Icepick Lobotomy",
        "track": 8,
        "year": 2014
    },
    {
        "album": "A Skeletal Domain",
        "albumartist": [
            "Cannibal Corpse"
        ],
        "albumartistid": [
            11
        ],
        "albumid": 15,
        "artist": [
            "Cannibal Corpse"
        ],
        "artistid": [
            11
        ],
        "comment": "",
        "disc": 0,
        "displayartist": "Cannibal Corpse",
        "duration": 205,
        "fanart": "",
        "file": "nfs:\\Music\\Cannibal Corpse - A Skeletal Domain\\09 - Vector Of Cruelty.mp3",
        "genre": [
            "Death Metal"
        ],
        "genreid": [
            11
        ],
        "label": "Vector Of Cruelty",
        "lastplayed": "",
        "lyrics": "",
        "musicbrainzalbumartistid": "",
        "musicbrainzalbumid": "",
        "musicbrainzartistid": "",
        "musicbrainztrackid": "",
        "playcount": 0,
        "rating": 0,
        "songid": 171,
        "thumbnail": "nfs:\\Music\\Cannibal Corpse - A Skeletal Domain\\Folder.jpg",
        "title": "Vector Of Cruelty",
        "track": 9,
        "year": 2014
    },
    {
        "album": "A Skeletal Domain",
        "albumartist": [
            "Cannibal Corpse"
        ],
        "albumartistid": [
            11
        ],
        "albumid": 15,
        "artist": [
            "Cannibal Corpse"
        ],
        "artistid": [
            11
        ],
        "comment": "",
        "disc": 0,
        "displayartist": "Cannibal Corpse",
        "duration": 222,
        "fanart": "",
        "file": "nfs:\\Music\\Cannibal Corpse - A Skeletal Domain\\10 - Bloodstained Cement.mp3",
        "genre": [
            "Death Metal"
        ],
        "genreid": [
            11
        ],
        "label": "Bloodstained Cement",
        "lastplayed": "",
        "lyrics": "",
        "musicbrainzalbumartistid": "",
        "musicbrainzalbumid": "",
        "musicbrainzartistid": "",
        "musicbrainztrackid": "",
        "playcount": 0,
        "rating": 0,
        "songid": 172,
        "thumbnail": "nfs:\\Music\\Cannibal Corpse - A Skeletal Domain\\Folder.jpg",
        "title": "Bloodstained Cement",
        "track": 10,
        "year": 2014
    },
    {
        "album": "A Skeletal Domain",
        "albumartist": [
            "Cannibal Corpse"
        ],
        "albumartistid": [
            11
        ],
        "albumid": 15,
        "artist": [
            "Cannibal Corpse"
        ],
        "artistid": [
            11
        ],
        "comment": "",
        "disc": 0,
        "displayartist": "Cannibal Corpse",
        "duration": 227,
        "fanart": "",
        "file": "nfs:\\Music\\Cannibal Corpse - A Skeletal Domain\\11 - Asphyxiate To Resuscitate.mp3",
        "genre": [
            "Death Metal"
        ],
        "genreid": [
            11
        ],
        "label": "Asphyxiate To Resuscitate",
        "lastplayed": "",
        "lyrics": "",
        "musicbrainzalbumartistid": "",
        "musicbrainzalbumid": "",
        "musicbrainzartistid": "",
        "musicbrainztrackid": "",
        "playcount": 0,
        "rating": 0,
        "songid": 173,
        "thumbnail": "nfs:\\Music\\Cannibal Corpse - A Skeletal Domain\\Folder.jpg",
        "title": "Asphyxiate To Resuscitate",
        "track": 11,
        "year": 2014
    },
    {
        "album": "A Skeletal Domain",
        "albumartist": [
            "Cannibal Corpse"
        ],
        "albumartistid": [
            11
        ],
        "albumid": 15,
        "artist": [
            "Cannibal Corpse"
        ],
        "artistid": [
            11
        ],
        "comment": "",
        "disc": 0,
        "displayartist": "Cannibal Corpse",
        "duration": 185,
        "fanart": "",
        "file": "nfs:\\Music\\Cannibal Corpse - A Skeletal Domain\\12 - Hollowed Bodies.mp3",
        "genre": [
            "Death Metal"
        ],
        "genreid": [
            11
        ],
        "label": "Hollowed Bodies",
        "lastplayed": "",
        "lyrics": "",
        "musicbrainzalbumartistid": "",
        "musicbrainzalbumid": "",
        "musicbrainzartistid": "",
        "musicbrainztrackid": "",
        "playcount": 0,
        "rating": 0,
        "songid": 174,
        "thumbnail": "nfs:\\Music\\Cannibal Corpse - A Skeletal Domain\\Folder.jpg",
        "title": "Hollowed Bodies",
        "track": 12,
        "year": 2014
    }
]