[
    {
        "album": "Santa Muerte",
        "albumartist": [
            "Broilers"
        ],
        "albumartistid": [
            9
        ],
        "albumid": 12,
        "artist": [
            "Broilers"
        ],
        "artistid": [
            9
        ],
        "comment": "",
        "disc": 0,
        "displayartist": "Broilers",
        "duration": 28,
        "fanart": "",
        "file": "nfs:\\Music\\Broilers - Santa Muerte\\01. Broilers - Preludio Santa Muerte.mp3",
        "genre": [
            "Punk"
        ],
        "genreid": [
            9
        ],
        "label": "Preludio: Santa Muerte",
        "lastplayed": "",
        "lyrics": "",
        "musicbrainzalbumartistid": "",
        "musicbrainzalbumid": "",
        "musicbrainzartistid": "",
        "musicbrainztrackid": "",
        "playcount": 0,
        "rating": 0,
        "songid": 119,
        "thumbnail": "nfs:\\Music\\Broilers - Santa Muerte\\folder.jpg",
        "title": "Preludio: Santa Muerte",
        "track": 1,
        "year": 2011
    },
    {
        "album": "Santa Muerte",
        "albumartist": [
            "Broilers"
        ],
        "albumartistid": [
            9
        ],
        "albumid": 12,
        "artist": [
            "Broilers"
        ],
        "artistid": [
            9
        ],
        "comment": "",
        "disc": 0,
        "displayartist": "Broilers",
        "duration": 202,
        "fanart": "",
        "file": "nfs:\\Music\\Broilers - Santa Muerte\\02. Broilers - Harter Weg (Go!).mp3",
        "genre": [
            "Punk"
        ],
        "genreid": [
            9
        ],
        "label": "Harter Weg (Go!)",
        "lastplayed": "",
        "lyrics": "",
        "musicbrainzalbumartistid": "",
        "musicbrainzalbumid": "",
        "musicbrainzartistid": "",
        "musicbrainztrackid": "",
        "playcount": 0,
        "rating": 0,
        "songid": 120,
        "thumbnail": "nfs:\\Music\\Broilers - Santa Muerte\\folder.jpg",
        "title": "Harter Weg (Go!)",
        "track": 2,
        "year": 2011
    },
    {
        "album": "Santa Muerte",
        "albumartist": [
            "Broilers"
        ],
        "albumartistid": [
            9
        ],
        "albumid": 12,
        "artist": [
            "Broilers"
        ],
        "artistid": [
            9
        ],
        "comment": "",
        "disc": 0,
        "displayartist": "Broilers",
        "duration": 197,
        "fanart": "",
        "file": "nfs:\\Music\\Broilers - Santa Muerte\\03. Broilers - In ein paar Jahren….mp3",
        "genre": [
            "Punk"
        ],
        "genreid": [
            9
        ],
        "label": "In ein paar Jahren…",
        "lastplayed": "",
        "lyrics": "",
        "musicbrainzalbumartistid": "",
        "musicbrainzalbumid": "",
        "musicbrainzartistid": "",
        "musicbrainztrackid": "",
        "playcount": 0,
        "rating": 0,
        "songid": 121,
        "thumbnail": "nfs:\\Music\\Broilers - Santa Muerte\\folder.jpg",
        "title": "In ein paar Jahren…",
        "track": 3,
        "year": 2011
    },
    {
        "album": "Santa Muerte",
        "albumartist": [
            "Broilers"
        ],
        "albumartistid": [
            9
        ],
        "albumid": 12,
        "artist": [
            "Broilers"
        ],
        "artistid": [
            9
        ],
        "comment": "",
        "disc": 0,
        "displayartist": "Broilers",
        "duration": 174,
        "fanart": "",
        "file": "nfs:\\Music\\Broilers - Santa Muerte\\04. Broilers - Tanzt Du noch einmal mit mir.mp3",
        "genre": [
            "Punk"
        ],
        "genreid": [
            9
        ],
        "label": "Tanzt Du noch einmal mit mir?",
        "lastplayed": "",
        "lyrics": "",
        "musicbrainzalbumartistid": "",
        "musicbrainzalbumid": "",
        "musicbrainzartistid": "",
        "musicbrainztrackid": "",
        "playcount": 0,
        "rating": 0,
        "songid": 122,
        "thumbnail": "nfs:\\Music\\Broilers - Santa Muerte\\folder.jpg",
        "title": "Tanzt Du noch einmal mit mir?",
        "track": 4,
        "year": 2011
    },
    {
        "album": "Santa Muerte",
        "albumartist": [
            "Broilers"
        ],
        "albumartistid": [
            9
        ],
        "albumid": 12,
        "artist": [
            "Broilers"
        ],
        "artistid": [
            9
        ],
        "comment": "",
        "disc": 0,
        "displayartist": "Broilers",
        "duration": 168,
        "fanart": "",
        "file": "nfs:\\Music\\Broilers - Santa Muerte\\05. Broilers - Schwarz, Grau, Weiß.mp3",
        "genre": [
            "Punk"
        ],
        "genreid": [
            9
        ],
        "label": "Schwarz, Grau, Weiß",
        "lastplayed": "",
        "lyrics": "",
        "musicbrainzalbumartistid": "",
        "musicbrainzalbumid": "",
        "musicbrainzartistid": "",
        "musicbrainztrackid": "",
        "playcount": 0,
        "rating": 0,
        "songid": 123,
        "thumbnail": "nfs:\\Music\\Broilers - Santa Muerte\\folder.jpg",
        "title": "Schwarz, Grau, Weiß",
        "track": 5,
        "year": 2011
    },
    {
        "album": "Santa Muerte",
        "albumartist": [
            "Broilers"
        ],
        "albumartistid": [
            9
        ],
        "albumid": 12,
        "artist": [
            "Broilers"
        ],
        "artistid": [
            9
        ],
        "comment": "",
        "disc": 0,
        "displayartist": "Broilers",
        "duration": 219,
        "fanart": "",
        "file": "nfs:\\Music\\Broilers - Santa Muerte\\06. Broilers - Verdammte Stille.mp3",
        "genre": [
            "Punk"
        ],
        "genreid": [
            9
        ],
        "label": "Verdammte Stille",
        "lastplayed": "",
        "lyrics": "",
        "musicbrainzalbumartistid": "",
        "musicbrainzalbumid": "",
        "musicbrainzartistid": "",
        "musicbrainztrackid": "",
        "playcount": 0,
        "rating": 0,
        "songid": 124,
        "thumbnail": "nfs:\\Music\\Broilers - Santa Muerte\\folder.jpg",
        "title": "Verdammte Stille",
        "track": 6,
        "year": 2011
    },
    {
        "album": "Santa Muerte",
        "albumartist": [
            "Broilers"
        ],
        "albumartistid": [
            9
        ],
        "albumid": 12,
        "artist": [
            "Broilers"
        ],
        "artistid": [
            9
        ],
        "comment": "",
        "disc": 0,
        "displayartist": "Broilers",
        "duration": 209,
        "fanart": "",
        "file": "nfs:\\Music\\Broilers - Santa Muerte\\07. Broilers - Gemeinsam.mp3",
        "genre": [
            "Punk"
        ],
        "genreid": [
            9
        ],
        "label": "Gemeinsam",
        "lastplayed": "",
        "lyrics": "",
        "musicbrainzalbumartistid": "",
        "musicbrainzalbumid": "",
        "musicbrainzartistid": "",
        "musicbrainztrackid": "",
        "playcount": 0,
        "rating": 0,
        "songid": 125,
        "thumbnail": "nfs:\\Music\\Broilers - Santa Muerte\\folder.jpg",
        "title": "Gemeinsam",
        "track": 7,
        "year": 2011
    },
    {
        "album": "Santa Muerte",
        "albumartist": [
            "Broilers"
        ],
        "albumartistid": [
            9
        ],
        "albumid": 12,
        "artist": [
            "Broilers"
        ],
        "artistid": [
            9
        ],
        "comment": "",
        "disc": 0,
        "displayartist": "Broilers",
        "duration": 188,
        "fanart": "",
        "file": "nfs:\\Music\\Broilers - Santa Muerte\\08. Broilers - 33 rpm.mp3",
        "genre": [
            "Punk"
        ],
        "genreid": [
            9
        ],
        "label": "33 rpm",
        "lastplayed": "",
        "lyrics": "",
        "musicbrainzalbumartistid": "",
        "musicbrainzalbumid": "",
        "musicbrainzartistid": "",
        "musicbrainztrackid": "",
        "playcount": 0,
        "rating": 0,
        "songid": 126,
        "thumbnail": "nfs:\\Music\\Broilers - Santa Muerte\\folder.jpg",
        "title": "33 rpm",
        "track": 8,
        "year": 2011
    },
    {
        "album": "Santa Muerte",
        "albumartist": [
            "Broilers"
        ],
        "albumartistid": [
            9
        ],
        "albumid": 12,
        "artist": [
            "Broilers"
        ],
        "artistid": [
            9
        ],
        "comment": "",
        "disc": 0,
        "displayartist": "Broilers",
        "duration": 244,
        "fanart": "",
        "file": "nfs:\\Music\\Broilers - Santa Muerte\\09. Broilers - Vom Scheitern (The World Is Yours, Nicht!).mp3",
        "genre": [
            "Punk"
        ],
        "genreid": [
            9
        ],
        "label": "Vom Scheitern (The World Is Yours, Nicht!)",
        "lastplayed": "",
        "lyrics": "",
        "musicbrainzalbumartistid": "",
        "musicbrainzalbumid": "",
        "musicbrainzartistid": "",
        "musicbrainztrackid": "",
        "playcount": 0,
        "rating": 0,
        "songid": 127,
        "thumbnail": "nfs:\\Music\\Broilers - Santa Muerte\\folder.jpg",
        "title": "Vom Scheitern (The World Is Yours, Nicht!)",
        "track": 9,
        "year": 2011
    },
    {
        "album": "Santa Muerte",
        "albumartist": [
            "Broilers"
        ],
        "albumartistid": [
            9
        ],
        "albumid": 12,
        "artist": [
            "Broilers"
        ],
        "artistid": [
            9
        ],
        "comment": "",
        "disc": 0,
        "displayartist": "Broilers",
        "duration": 164,
        "fanart": "",
        "file": "nfs:\\Music\\Broilers - Santa Muerte\\10. Broilers - Alles geht weiter.mp3",
        "genre": [
            "Punk"
        ],
        "genreid": [
            9
        ],
        "label": "Alles geht weiter",
        "lastplayed": "",
        "lyrics": "",
        "musicbrainzalbumartistid": "",
        "musicbrainzalbumid": "",
        "musicbrainzartistid": "",
        "musicbrainztrackid": "",
        "playcount": 0,
        "rating": 0,
        "songid": 128,
        "thumbnail": "nfs:\\Music\\Broilers - Santa Muerte\\folder.jpg",
        "title": "Alles geht weiter",
        "track": 10,
        "year": 2011
    },
    {
        "album": "Santa Muerte",
        "albumartist": [
            "Broilers"
        ],
        "albumartistid": [
            9
        ],
        "albumid": 12,
        "artist": [
            "Broilers"
        ],
        "artistid": [
            9
        ],
        "comment": "",
        "disc": 0,
        "displayartist": "Broilers",
        "duration": 193,
        "fanart": "",
        "file": "nfs:\\Music\\Broilers - Santa Muerte\\11. Broilers - Weckt die Toten.mp3",
        "genre": [
            "Punk"
        ],
        "genreid": [
            9
        ],
        "label": "Weckt die Toten",
        "lastplayed": "",
        "lyrics": "",
        "musicbrainzalbumartistid": "",
        "musicbrainzalbumid": "",
        "musicbrainzartistid": "",
        "musicbrainztrackid": "",
        "playcount": 0,
        "rating": 0,
        "songid": 129,
        "thumbnail": "nfs:\\Music\\Broilers - Santa Muerte\\folder.jpg",
        "title": "Weckt die Toten",
        "track": 11,
        "year": 2011
    },
    {
        "album": "Santa Muerte",
        "albumartist": [
            "Broilers"
        ],
        "albumartistid": [
            9
        ],
        "albumid": 12,
        "artist": [
            "Broilers"
        ],
        "artistid": [
            9
        ],
        "comment": "",
        "disc": 0,
        "displayartist": "Broilers",
        "duration": 179,
        "fanart": "",
        "file": "nfs:\\Music\\Broilers - Santa Muerte\\12. Broilers - Wie weit wir gehen.mp3",
        "genre": [
            "Punk"
        ],
        "genreid": [
            9
        ],
        "label": "Wie weit wir gehen",
        "lastplayed": "",
        "lyrics": "",
        "musicbrainzalbumartistid": "",
        "musicbrainzalbumid": "",
        "musicbrainzartistid": "",
        "musicbrainztrackid": "",
        "playcount": 0,
        "rating": 0,
        "songid": 130,
        "thumbnail": "nfs:\\Music\\Broilers - Santa Muerte\\folder.jpg",
        "title": "Wie weit wir gehen",
        "track": 12,
        "year": 2011
    },
    {
        "album": "Santa Muerte",
        "albumartist": [
            "Broilers"
        ],
        "albumartistid": [
            9
        ],
        "albumid": 12,
        "artist": [
            "Broilers"
        ],
        "artistid": [
            9
        ],
        "comment": "",
        "disc": 0,
        "displayartist": "Broilers",
        "duration": 184,
        "fanart": "",
        "file": "nfs:\\Music\\Broilers - Santa Muerte\\13. Broilers - Stoßen wir an.mp3",
        "genre": [
            "Punk"
        ],
        "genreid": [
            9
        ],
        "label": "Stoßen wir an",
        "lastplayed": "",
        "lyrics": "",
        "musicbrainzalbumartistid": "",
        "musicbrainzalbumid": "",
        "musicbrainzartistid": "",
        "musicbrainztrackid": "",
        "playcount": 0,
        "rating": 0,
        "songid": 131,
        "thumbnail": "nfs:\\Music\\Broilers - Santa Muerte\\folder.jpg",
        "title": "Stoßen wir an",
        "track": 13,
        "year": 2011
    },
    {
        "album": "Santa Muerte",
        "albumartist": [
            "Broilers"
        ],
        "albumartistid": [
            9
        ],
        "albumid": 12,
        "artist": [
            "Broilers"
        ],
        "artistid": [
            9
        ],
        "comment": "",
        "disc": 0,
        "displayartist": "Broilers",
        "duration": 207,
        "fanart": "",
        "file": "nfs:\\Music\\Broilers - Santa Muerte\\14. Broilers - Singe, Seufze & Saufe.mp3",
        "genre": [
            "Punk"
        ],
        "genreid": [
            9
        ],
        "label": "Singe, Seufze & Saufe",
        "lastplayed": "",
        "lyrics": "",
        "musicbrainzalbumartistid": "",
        "musicbrainzalbumid": "",
        "musicbrainzartistid": "",
        "musicbrainztrackid": "",
        "playcount": 0,
        "rating": 0,
        "songid": 132,
        "thumbnail": "nfs:\\Music\\Broilers - Santa Muerte\\folder.jpg",
        "title": "Singe, Seufze & Saufe",
        "track": 14,
        "year": 2011
    }
]